haram_sum/__init__.py
haram_sum/sum.py
haram_sum-0.1.6.dist-info/METADATA
haram_sum-0.1.6.dist-info/WHEEL
haram_sum-0.1.6.dist-info/entry_points.txt
haram_sum-0.1.6.dist-info/top_level.txt
haram_sum-0.1.6.dist-info/RECORD
