Metadata-Version: 2.1
Name: haram_sum
Version: 0.1.6
Summary: Default template for PDM package
Author-email: HaramSs <haram8274@gmail.com>
License: MIT
Requires-Python: >=3.9
